wedgie/__init__.py
wedgie/asyncio_workaround.py
wedgie/common/__init__.py
wedgie/common/event_broker.py
wedgie/resource_cache/__init__.py
wedgie/resource_cache/resource_cache.py
wedgie/resource_cache/resource_cache_async.py
wedgie-0.0.5.13.dist-info/LICENSE
wedgie-0.0.5.13.dist-info/METADATA
wedgie-0.0.5.13.dist-info/WHEEL
wedgie-0.0.5.13.dist-info/top_level.txt
wedgie-0.0.5.13.dist-info/RECORD
