Metadata-Version: 2.1
Name: wedgie
Version: 0.0.5.13
Summary: A public Python package for miscellaneous reusable functionality
Home-page: https://github.com/deathbywedgie/wedgie-py
Author: Chad Roberts
Author-email: jcbroberts@gmail.com
Classifier: Intended Audience :: System Administrators
Classifier: Intended Audience :: Information Technology
Classifier: Programming Language :: Python :: 3
Classifier: License :: OSI Approved :: MIT License
Classifier: Operating System :: OS Independent
Classifier: Natural Language :: English
Requires-Python: >=3.7
License-File: LICENSE
Requires-Dist: structlog
Requires-Dist: tinydb >=4.8.0
Requires-Dist: tabulate >=0.9.0
